symMath_adasneves127/__init__.py
symMath_adasneves127/equation.py
symMath_adasneves127/token.py
symMath_adasneves127/token_maker.py
symMath_adasneves127/tree_maker.py
symMath_adasneves127/tree_node.py
mathsym_adasneves-1.1.4.dist-info/LICENSE
mathsym_adasneves-1.1.4.dist-info/METADATA
mathsym_adasneves-1.1.4.dist-info/WHEEL
mathsym_adasneves-1.1.4.dist-info/top_level.txt
mathsym_adasneves-1.1.4.dist-info/RECORD
