Metadata-Version: 2.1
Name: mathsym-adasneves
Version: 1.1.4
Summary: A small example package
Author-email: Alex Dasneves <adasneves@adasneves.info>
Project-URL: Homepage, https://github.com/adasneves127/Symmath
Project-URL: Bug Tracker, https://github.com/adasneves127/Symmath/issues
Classifier: Programming Language :: Python :: 3
Classifier: License :: OSI Approved :: MIT License
Classifier: Operating System :: OS Independent
Requires-Python: >=3.10
License-File: LICENSE
